stac_geoparquet/__init__.py
stac_geoparquet/_compat.py
stac_geoparquet/_version.py
stac_geoparquet/cli.py
stac_geoparquet/from_arrow.py
stac_geoparquet/json_reader.py
stac_geoparquet/pc_runner.py
stac_geoparquet/pgstac_reader.py
stac_geoparquet/py.typed
stac_geoparquet/stac_geoparquet.py
stac_geoparquet/to_arrow.py
stac_geoparquet/to_parquet.py
stac_geoparquet/utils.py
stac_geoparquet/arrow/__init__.py
stac_geoparquet/arrow/_api.py
stac_geoparquet/arrow/_batch.py
stac_geoparquet/arrow/_constants.py
stac_geoparquet/arrow/_crs.py
stac_geoparquet/arrow/_delta_lake.py
stac_geoparquet/arrow/_from_arrow.py
stac_geoparquet/arrow/_to_arrow.py
stac_geoparquet/arrow/_to_parquet.py
stac_geoparquet/arrow/_util.py
stac_geoparquet/arrow/types.py
stac_geoparquet/arrow/_schema/models.py
stac_geoparquet-0.7.0.dist-info/METADATA
stac_geoparquet-0.7.0.dist-info/WHEEL
stac_geoparquet-0.7.0.dist-info/entry_points.txt
stac_geoparquet-0.7.0.dist-info/licenses/LICENSE
stac_geoparquet-0.7.0.dist-info/RECORD
