Metadata-Version: 2.4
Name: stac-geoparquet
Version: 0.7.0
Dynamic: Summary
Project-URL: Home, https://github.com/stac-utils/stac-geoparquet
Author-email: Tom Augspurger <taugspurger@microsoft.com>
License: The MIT License (MIT)
License-File: LICENSE
Classifier: License :: OSI Approved :: MIT License
Requires-Python: >=3.9
Requires-Dist: ciso8601
Requires-Dist: deltalake
Requires-Dist: geopandas
Requires-Dist: orjson
Requires-Dist: packaging
Requires-Dist: pandas
Requires-Dist: pyarrow!=19.0.0,>=16
Requires-Dist: pyproj
Requires-Dist: pystac
Requires-Dist: shapely
Requires-Dist: typing-extensions; python_version < '3.11'
Provides-Extra: pc
Requires-Dist: adlfs; extra == 'pc'
Requires-Dist: azure-data-tables; extra == 'pc'
Requires-Dist: psycopg[binary,pool]; extra == 'pc'
Requires-Dist: pypgstac; extra == 'pc'
Requires-Dist: tqdm; extra == 'pc'
Provides-Extra: pgstac
Requires-Dist: fsspec; extra == 'pgstac'
Requires-Dist: psycopg[binary,pool]; extra == 'pgstac'
Requires-Dist: pypgstac; extra == 'pgstac'
Requires-Dist: python-dateutil; extra == 'pgstac'
Requires-Dist: tqdm; extra == 'pgstac'
